sealang.so
clang/__init__.py
clang/cindex.py
clang/enumerations.py
sealang-3.9.dev259750.dist-info/DESCRIPTION.rst
sealang-3.9.dev259750.dist-info/METADATA
sealang-3.9.dev259750.dist-info/RECORD
sealang-3.9.dev259750.dist-info/WHEEL
sealang-3.9.dev259750.dist-info/metadata.json
sealang-3.9.dev259750.dist-info/pbr.json
sealang-3.9.dev259750.dist-info/top_level.txt
