Metadata-Version: 2.0
Name: sealang
Version: 3.9.dev259750
Summary: An extended set of Python bindings for libclang
Home-page: http://github.com/pybee/sealang
Author: LLVM team and Russell Keith-Magee
Author-email: russell@keith-magee.com
License: License :: OSI Approved :: University of Illinois/NCSA Open Source License
Keywords: llvm,clang,libclang
Platform: UNKNOWN
Classifier: Intended Audience :: Developers
Classifier: License :: OSI Approved :: University of Illinois/NCSA Open Source License
Classifier: Programming Language :: Python
Classifier: Development Status :: 5 - Production/Stable
Classifier: Topic :: Software Development :: Compilers
Classifier: Programming Language :: Python :: 3
Classifier: Programming Language :: Python :: 3.4
Classifier: Programming Language :: Python :: 3.5
Classifier: Programming Language :: Python :: 2
Classifier: Programming Language :: Python :: 2.7
